Workbook

Sheet 4. Resumo
A1: RESUMO - custo e lucro das receitas
A2: Esta aba só mostra resultados. Para mudar preços vá em '1. Insumos'; para mudar quantidades e preço de venda vá nas abas das receitas.
A4: Indicador | B4: Receita 1 - Café | C4: Receita 2 - Cappuccino
A5: Rendimento (potes por lote) | B5: ='2. Café'!$B$4 -> 4 | C5: ='3. Cappuccino'!$B$4 -> 4
A6: Custo total do lote | B6: ='2. Café'!$E$28 -> 29.03875 | C6: ='3. Cappuccino'!$E$30 -> 36.03775
A7: CUSTO POR POTE | B7: ='2. Café'!$E$29 -> 7.2596875 | C7: ='3. Cappuccino'!$E$31 -> 9.0094375
A8: Preço de venda por pote | B8: ='2. Café'!$E$30 -> 25 | C8: ='3. Cappuccino'!$E$32 -> 25
A9: LUCRO POR POTE | B9: ='2. Café'!$E$31 -> 17.740313 | C9: ='3. Cappuccino'!$E$33 -> 15.990562
A10: Lucro do lote | B10: ='2. Café'!$E$31*'2. Café'!$B$4 -> 70.96125 | C10: ='3. Cappuccino'!$E$33*'3. Cappuccino'!$B$4 -> 63.96225
A11: Margem de lucro | B11: =IF('2. Café'!$E$30=0,0,'2. Café'!$E$31/'2. Café'!$E$30) -> 0.7096125 | C11: =IF('3. Cappuccino'!$E$32=0,0,'3. Cappuccino'!$E$33/'3. Cappuccino'!$E$32) -> 0.6396225
A13: SIMULADOR DE PRODUÇÃO
A14: Quantos lotes você vai produzir? | B14: 1 | C14: 1 | D14: <- edite estes dois números (amarelo)
A15: Potes produzidos | B15: ='2. Café'!$B$4*B$14 -> 4 | C15: ='3. Cappuccino'!$B$4*C$14 -> 4
A16: Custo total | B16: ='2. Café'!$E$28*B$14 -> 29.03875 | C16: ='3. Cappuccino'!$E$30*C$14 -> 36.03775
A17: Faturamento total | B17: ='2. Café'!$E$30*'2. Café'!$B$4*B$14 -> 100 | C17: ='3. Cappuccino'!$E$32*'3. Cappuccino'!$B$4*C$14 -> 100
A18: Lucro total | B18: ='2. Café'!$E$31*'2. Café'!$B$4*B$14 -> 70.96125 | C18: ='3. Cappuccino'!$E$33*'3. Cappuccino'!$B$4*C$14 -> 63.96225
A19: LUCRO TOTAL (as duas receitas somadas) | B19: =B18+C18 -> 134.9235
A21: COMO USAR
A22: 1) Aba '1. Insumos': atualize o preço e o tamanho das embalagens que você compra (células amarelas).
A23: 2) Abas '2. Café' e '3. Cappuccino': ajuste o rendimento, as quantidades da receita e o PREÇO DE VENDA por pote.
A24: 3) Se quiser, some gás/energia/mão de obra em 'Outros custos do lote'.
A25: 4) Volte aqui no Resumo para ver custo por pote, lucro e margem - e simule quantos lotes produzir.
A26: REGRA: só edite as células AMARELAS. As cinzas, verdes e laranjas são fórmulas e se atualizam sozinhas.

Sheet 1. Insumos
A1: TABELA DE INSUMOS - preços de compra
A2: Altere aqui o preço e o tamanho da embalagem que você compra. Todas as receitas recalculam sozinhas.
A3: AMARELO = você edita | CINZA = calculado automaticamente (não digite)
A5: Insumo | B5: Preço da embalagem (R$) | C5: Qtd. na embalagem | D5: Unidade | E5: Custo por unidade (R$)
A6: Café solúvel | B6: 11.24 | C6: 50 | D6: g | E6: =IF(C6=0,0,B6/C6) -> 0.2248
A7: Açúcar | B7: 7.99 | C7: 2000 | D7: g | E7: =IF(C7=0,0,B7/C7) -> 0.003995
A8: Cacau 50% | B8: 35 | C8: 200 | D8: g | E8: =IF(C8=0,0,B8/C8) -> 0.175
A9: Canela em pó | B9: 6.99 | C9: 20 | D9: g | E9: =IF(C9=0,0,B9/C9) -> 0.3495
A10: Água | B10: 0 | C10: 1000 | D10: ml | E10: =IF(C10=0,0,B10/C10) -> 0
A11: Pote de vidro | B11: 3.45 | C11: 1 | D11: un | E11: =IF(C11=0,0,B11/C11) -> 3.45
A12: Adesivo frente | B12: 0.44 | C12: 1 | D12: un | E12: =IF(C12=0,0,B12/C12) -> 0.44
A13: Adesivo verso | B13: 0.31 | C13: 1 | D13: un | E13: =IF(C13=0,0,B13/C13) -> 0.31
A15: A água não entra no custo (preço R$ 0,00). Se quiser considerá-la, basta preencher o preço acima.

Sheet 2. Café
A1: RECEITA 1 - CAFÉ (tradicional)
A2: AMARELO = você edita | CINZA / VERDE / LARANJA = calculado automaticamente
A4: Rendimento do lote (potes) | B4: 4 | C4: <- quantos potes saem de uma receita
A6: INGREDIENTES (quantidade para o lote inteiro)
A7: Ingrediente | B7: Qtd. no lote | C7: Unidade | D7: Custo unitário (R$) | E7: Custo no lote (R$)
A8: Café solúvel | B8: 50 | C8: g | D8: =IFERROR(VLOOKUP($A8,'1. Insumos'!$A$6:$E$13,5,FALSE),0) -> 0.2248 | E8: =B8*D8 -> 11.24
A9: Açúcar | B9: 250 | C9: g | D9: =IFERROR(VLOOKUP($A9,'1. Insumos'!$A$6:$E$13,5,FALSE),0) -> 0.003995 | E9: =B9*D9 -> 0.99875
A10: Água | B10: 150 | C10: ml | D10: =IFERROR(VLOOKUP($A10,'1. Insumos'!$A$6:$E$13,5,FALSE),0) -> 0 | E10: =B10*D10 -> 0
A11: Subtotal ingredientes (lote) | E11: =SUM(E8:E10) -> 12.23875
A13: EMBALAGEM E RÓTULOS (por pote)
A14: Item | B14: Qtd. por pote | C14: Unidade | D14: Custo unitário (R$) | E14: Custo no lote (R$)
A15: Pote de vidro | B15: 1 | C15: un | D15: =IFERROR(VLOOKUP($A15,'1. Insumos'!$A$6:$E$13,5,FALSE),0) -> 3.45 | E15: =B15*D15*$B$4 -> 13.8
A16: Adesivo frente | B16: 1 | C16: un | D16: =IFERROR(VLOOKUP($A16,'1. Insumos'!$A$6:$E$13,5,FALSE),0) -> 0.44 | E16: =B16*D16*$B$4 -> 1.76
A17: Adesivo verso | B17: 1 | C17: un | D17: =IFERROR(VLOOKUP($A17,'1. Insumos'!$A$6:$E$13,5,FALSE),0) -> 0.31 | E17: =B17*D17*$B$4 -> 1.24
A18: Subtotal embalagem (lote) | E18: =SUM(E15:E17) -> 16.8
A20: OUTROS CUSTOS DO LOTE (opcional)
A21: Descrição | E21: Valor no lote (R$)
A22: Gás / energia | E22: 0
A23: Mão de obra | E23: 0
A24: Outros | E24: 0
A25: Subtotal outros custos (lote) | E25: =SUM(E22:E24) -> 0
A27: RESULTADO
A28: CUSTO TOTAL DO LOTE | E28: =$E$11+$E$18+$E$25 -> 29.03875
A29: CUSTO POR POTE | E29: =IF($B$4=0,0,$E$28/$B$4) -> 7.2596875
A30: PREÇO DE VENDA POR POTE | E30: 25 | F30: <- digite aqui o preço que você cobra
A31: Lucro por pote | E31: =$E$30-$E$29 -> 17.740313
A32: Faturamento do lote | E32: =$E$30*$B$4 -> 100
A33: Lucro do lote | E33: =$E$31*$B$4 -> 70.96125
A34: Margem de lucro (%) | E34: =IF($E$30=0,0,$E$31/$E$30) -> 0.7096125 | F34: lucro sobre o preço de venda
A35: Markup (multiplicador) | E35: =IF($E$29=0,0,$E$30/$E$29) -> 3.4436744 | F35: quantas vezes o custo

Sheet 3. Cappuccino
A1: RECEITA 2 - CAPPUCCINO
A2: AMARELO = você edita | CINZA / VERDE / LARANJA = calculado automaticamente
A4: Rendimento do lote (potes) | B4: 4 | C4: <- quantos potes saem de uma receita
A6: INGREDIENTES (quantidade para o lote inteiro)
A7: Ingrediente | B7: Qtd. no lote | C7: Unidade | D7: Custo unitário (R$) | E7: Custo no lote (R$)
A8: Café solúvel | B8: 50 | C8: g | D8: =IFERROR(VLOOKUP($A8,'1. Insumos'!$A$6:$E$13,5,FALSE),0) -> 0.2248 | E8: =B8*D8 -> 11.24
A9: Açúcar | B9: 250 | C9: g | D9: =IFERROR(VLOOKUP($A9,'1. Insumos'!$A$6:$E$13,5,FALSE),0) -> 0.003995 | E9: =B9*D9 -> 0.99875
A10: Água | B10: 150 | C10: ml | D10: =IFERROR(VLOOKUP($A10,'1. Insumos'!$A$6:$E$13,5,FALSE),0) -> 0 | E10: =B10*D10 -> 0
A11: Cacau 50% | B11: 36 | C11: g | D11: =IFERROR(VLOOKUP($A11,'1. Insumos'!$A$6:$E$13,5,FALSE),0) -> 0.175 | E11: =B11*D11 -> 6.3
A12: Canela em pó | B12: 2 | C12: g | D12: =IFERROR(VLOOKUP($A12,'1. Insumos'!$A$6:$E$13,5,FALSE),0) -> 0.3495 | E12: =B12*D12 -> 0.699
A13: Subtotal ingredientes (lote) | E13: =SUM(E8:E12) -> 19.23775
A15: EMBALAGEM E RÓTULOS (por pote)
A16: Item | B16: Qtd. por pote | C16: Unidade | D16: Custo unitário (R$) | E16: Custo no lote (R$)
A17: Pote de vidro | B17: 1 | C17: un | D17: =IFERROR(VLOOKUP($A17,'1. Insumos'!$A$6:$E$13,5,FALSE),0) -> 3.45 | E17: =B17*D17*$B$4 -> 13.8
A18: Adesivo frente | B18: 1 | C18: un | D18: =IFERROR(VLOOKUP($A18,'1. Insumos'!$A$6:$E$13,5,FALSE),0) -> 0.44 | E18: =B18*D18*$B$4 -> 1.76
A19: Adesivo verso | B19: 1 | C19: un | D19: =IFERROR(VLOOKUP($A19,'1. Insumos'!$A$6:$E$13,5,FALSE),0) -> 0.31 | E19: =B19*D19*$B$4 -> 1.24
A20: Subtotal embalagem (lote) | E20: =SUM(E17:E19) -> 16.8
A22: OUTROS CUSTOS DO LOTE (opcional)
A23: Descrição | E23: Valor no lote (R$)
A24: Gás / energia | E24: 0
A25: Mão de obra | E25: 0
A26: Outros | E26: 0
A27: Subtotal outros custos (lote) | E27: =SUM(E24:E26) -> 0
A29: RESULTADO
A30: CUSTO TOTAL DO LOTE | E30: =$E$13+$E$20+$E$27 -> 36.03775
A31: CUSTO POR POTE | E31: =IF($B$4=0,0,$E$30/$B$4) -> 9.0094375
A32: PREÇO DE VENDA POR POTE | E32: 25 | F32: <- digite aqui o preço que você cobra
A33: Lucro por pote | E33: =$E$32-$E$31 -> 15.990562
A34: Faturamento do lote | E34: =$E$32*$B$4 -> 100
A35: Lucro do lote | E35: =$E$33*$B$4 -> 63.96225
A36: Margem de lucro (%) | E36: =IF($E$32=0,0,$E$33/$E$32) -> 0.6396225 | F36: lucro sobre o preço de venda
A37: Markup (multiplicador) | E37: =IF($E$31=0,0,$E$32/$E$31) -> 2.774868 | F37: quantas vezes o custo
